TARNet/__init__.py
TARNet/layers/MLP.py
TARNet/layers/extract.py
TARNet/layers/gather.py
TARNet/layers/split.py
TARNet/models/TARNet.py
TARNet-1.0.dist-info/LICENSE
TARNet-1.0.dist-info/METADATA
TARNet-1.0.dist-info/WHEEL
TARNet-1.0.dist-info/top_level.txt
TARNet-1.0.dist-info/RECORD
