Metadata-Version: 2.1
Name: TARNet
Version: 1.0
Summary: TARNet Model with tensorflow 2 API.
Author-email: Arnaud Victor Petit <arnaud.petit39@gmail.com>
Project-URL: Homepage, https://github.com/arnaud39/TARNet
Project-URL: Bug Tracker, https://github.com/arnaud39/TARNet/issues
Classifier: Programming Language :: Python :: 3
Classifier: License :: OSI Approved :: MIT License
Classifier: Operating System :: OS Independent
Requires-Python: >=3.7
License-File: LICENSE
